distlock/__init__.py
distlock/__version__.py
distlock/distlock.py
distlock-0.0.1.dev1.dist-info/LICENSE
distlock-0.0.1.dev1.dist-info/METADATA
distlock-0.0.1.dev1.dist-info/WHEEL
distlock-0.0.1.dev1.dist-info/top_level.txt
distlock-0.0.1.dev1.dist-info/RECORD
