Metadata-Version: 2.1
Name: distlock
Version: 0.0.1.dev1
Summary: Distributed locks with Redis
Home-page: https://github.com/hnimminh/distlock
Author: Minh Minh
Author-email: hnimminh@outlook.com
License: MIT
Platform: UNKNOWN
Classifier: Development Status :: 4 - Beta
Classifier: Intended Audience :: Developers
Classifier: Programming Language :: Python
Classifier: License :: OSI Approved :: MIT License
Classifier: Programming Language :: Python :: 3
Classifier: Programming Language :: Python :: 3.6
Classifier: Programming Language :: Python :: 3.7
Classifier: Programming Language :: Python :: 3.8
Classifier: Programming Language :: Python :: 3.9
Requires-Dist: redis
